sumproduct.py
sumproduct-0.0.7.dist-info/DESCRIPTION.rst
sumproduct-0.0.7.dist-info/METADATA
sumproduct-0.0.7.dist-info/RECORD
sumproduct-0.0.7.dist-info/WHEEL
sumproduct-0.0.7.dist-info/metadata.json
sumproduct-0.0.7.dist-info/top_level.txt
