Metadata-Version: 2.0
Name: sumproduct
Version: 0.0.7
Summary: The sum-product algorithm. (Loopy) Belief Propagation (message passing) for factor graphs
Home-page: http://github.com/ilyakava/sumproduct/
Author: Ilya Kavalerov
Author-email: ilyakavalerov@gmail.com
License: MIT
Platform: UNKNOWN
Classifier: Natural Language :: English
Classifier: License :: OSI Approved :: MIT License
Classifier: Operating System :: OS Independent
Classifier: Programming Language :: Python
Classifier: Programming Language :: Python :: 2.7
Classifier: Programming Language :: Python :: 3.5
Classifier: Intended Audience :: Science/Research
Classifier: Topic :: Scientific/Engineering :: Artificial Intelligence
Classifier: Topic :: Scientific/Engineering :: Mathematics
Classifier: Topic :: Software Development :: Libraries :: Python Modules
Requires-Dist: numpy
